pynky/__init__.py
pynky/poset.py
pynky-0.0.3.dist-info/LICENSE
pynky-0.0.3.dist-info/METADATA
pynky-0.0.3.dist-info/WHEEL
pynky-0.0.3.dist-info/top_level.txt
pynky-0.0.3.dist-info/RECORD
