Metadata-Version: 2.1
Name: pynky
Version: 0.0.3
Summary: Math utils
Home-page: https://github.com/thorwhalen/newut/tree/master/pynky
Author: Thor Whalen
License: mit
Platform: any
License-File: LICENSE
